verilog/task3/subtask1/alu.v

//if select line s=00101, out=a+b
//if s=00111, out = a + mod b
//if s=00110, out= a-b;
//if s=01000, a*b
//01011 --> a/b
//01100 --> a <<2
//10100 --> a>>2

module alu (a,b,s,clk,out);
    input [39:0]a,b;
    input [4:0]s;
    input clk;
    
    //reg [39:0]c,d;

    output [39:0]out;
    reg [39:0]out;
    
    always @ (posedge clk) begin
    
        if (s==5'b00101)
            out = a+b;
        else if (s==5'b00111) begin
            if (b>0)
                out = a + b;
            else
                out = a-b;
            end
        else if (s==5'b00110)
            out = a-b;
        else if (s==5'b01000) begin
            if (b>0)
                out = a - b;
            else
                out = a+b;
            end
        else if (s==5'b01011)
            out = a*b;
        else if (s==5'b01100)
            out = a/b;
        else if (s==5'b10100)
            out = a<<2;
        else if (s==5'b010101)
            out = a>>2;
    end
endmodule

verilog/task3/subtask1/tb.v
`timescale 1ns/1ps
module tb;

reg [39:0]a,b;
reg clk;
reg [4:0]s;
wire [39:0]out;

alu uut (.a(a), .b(b), .s(s), .clk(clk), .out(out));

initial begin
$dumpfile("alua.vcd");
$dumpvars(0, tb);
a= 40'h000000000b;
b= 40'h0000000003;
clk=0;
s= 5'b00101;
end

always
begin
#3 clk=~clk;
end

initial
begin
#10 s = 5'b00111;
#10 s = 5'b00110;
#10 s = 5'b01000;
#10 s = 5'b01011;
#10 s = 5'b01100;
#10 s = 5'b10100;
#10 s = 5'b10101;
#10;
$finish;
end


endmodule

verilog/task3/subtask1/alua.vcd
$date
	Tue Jul 18 12:00:51 2023
$end
$version
	Icarus Verilog
$end
$timescale
	1ps
$end
$scope module tb $end
$var wire 40 ! out [39:0] $end
$var reg 40 " a [39:0] $end
$var reg 40 # b [39:0] $end
$var reg 1 $ clk $end
$var reg 5 % s [4:0] $end
$scope module uut $end
$var wire 40 & a [39:0] $end
$var wire 40 ' b [39:0] $end
$var wire 1 $ clk $end
$var wire 5 ( s [4:0] $end
$var reg 40 ) out [39:0] $end
$upscope $end
$upscope $end
$enddefinitions $end
#0
$dumpvars
bx )
b101 (
b11 '
b1011 &
b101 %
0$
b11 #
b1011 "
bx !
$end
#3000
b1110 !
b1110 )
1$
#6000
0$
#9000
1$
#10000
b111 %
b111 (
#12000
0$
#15000
1$
#18000
0$
#20000
b110 %
b110 (
#21000
b1000 !
b1000 )
1$
#24000
0$
#27000
1$
#30000
0$
b1000 %
b1000 (
#33000
1$
#36000
0$
#39000
1$
#40000
b1011 %
b1011 (
#42000
0$
#45000
b100001 !
b100001 )
1$
#48000
0$
#50000
b1100 %
b1100 (
#51000
b11 !
b11 )
1$
#54000
0$
#57000
1$
#60000
0$
b10100 %
b10100 (
#63000
b101100 !
b101100 )
1$
#66000
0$
#69000
1$
#70000
b10101 %
b10101 (
#72000
0$
#75000
b10 !
b10 )
1$
