verilog/task1/subtask1a_not_submit/mux_struct.v
`timescale 10ns/10ps
`default_nettype none

module mux_struct (
    input wire [1:0]I,
    input wire S,
    output wire Y
);
    wire Sbar,w1,w2;
    
    not inv1(Sbar,S);

    and and1(w1, Sbar, I[0]);
    and and2(w2, S, I[1]);

    or or1(Y, w1, w2);

endmodule

verilog/task1/subtask1a_not_submit/mux_rtl.v
//`timescale 10ns/1ps
module mux_rtl(
    input [1:0]I,
    input S,
    output Y
);
    assign Y = S ? I[1]: I[0];
    
endmodule

verilog/task1/subtask1a_not_submit/mux_tb.v
//`include "mux_struct.v"
`timescale 1ns/1ps
module mux_tb;
    reg [1:0]I;
    reg S;
    wire Y;

    mux_rtl M1(.I(I), .S(S), .Y(Y));

    task delay;
    begin
      #10;
    end
    endtask

    task stimulus (input [1:0]a, input select);
    begin
        I = a;
        S = select;
    end
    endtask

    task initialize;
    begin
      I = 2'b00;
      S = 1'b0;
    end
    endtask

    integer i,j;
    initial begin
        $dumpfile("mux_rtl.vcd");
        $dumpvars(0,mux_tb);

        initialize;
        delay;

        for(i=0 ; i<4; i=i+1) begin
          for(j=0; j<2; j=j+1) begin
            stimulus(i,j);
            delay;
          end
        end

        $finish;
    end

    initial $monitor($time,"ns S = %b, I1 = %b, I0 = %b, Y = %b",S, I[1], I[0], Y);


endmodule

verilog/task1/subtask1a_not_submit/mux_rtl.vcd
$date
	Thu Jul 13 11:53:29 2023
$end
$version
	Icarus Verilog
$end
$timescale
	1ps
$end
$scope module mux_tb $end
$var wire 1 ! Y $end
$var reg 2 " I [1:0] $end
$var reg 1 # S $end
$var integer 32 $ i [31:0] $end
$var integer 32 % j [31:0] $end
$scope module M1 $end
$var wire 2 & I [1:0] $end
$var wire 1 # S $end
$var wire 1 ! Y $end
$upscope $end
$scope task delay $end
$upscope $end
$scope task initialize $end
$upscope $end
$scope task stimulus $end
$var reg 2 ' a [1:0] $end
$var reg 1 ( select $end
$upscope $end
$upscope $end
$enddefinitions $end
#0
$dumpvars
x(
bx '
b0 &
bx %
bx $
0#
b0 "
0!
$end
#10000
0(
b0 '
b0 %
b0 $
#20000
1#
1(
b1 %
#30000
1!
0#
b1 "
b1 &
0(
b1 '
b1 $
b0 %
#40000
0!
1#
1(
b1 %
#50000
0#
b10 "
b10 &
0(
b10 '
b10 $
b0 %
#60000
1!
1#
1(
b1 %
#70000
0#
b11 "
b11 &
0(
b11 '
b11 $
b0 %
#80000
1#
1(
b1 %
#90000
b100 $
b10 %
