verilog/task5/q6/q6_alu.v
module alu (a,b,s,clk,out);
    input [39:0]a,b;
    input [4:0]s;
    input clk;
    
    reg [39:0]c,d;

    output [39:0]out;
    reg [39:0]out;
    
    integer i;
    always @ (posedge clk) begin
    
        if (s==5'b00101)
            out = a+b;
        else if (s==5'b00111) begin
            if (b>0)
                out = a + b;
            else
                out = a-b;
            end
        else if (s==5'b00110)
            out = a-b;
        else if (s==5'b01000)
            out = a*b;
        else if (s==5'b01011)
            out = a/b;
        else if (s==5'b10100) begin
            for(i=0; i<38; i++) begin
                c[i]= a[i+2];
                c[38] = 0;
                c[39] =0;   
            end

            out = c;
        end
        else if (s==5'b01100) begin
            for(i=0; i<38; i++) begin
                d[i+2]= a[i];
                d[0] = 0;
                d[1] = 0;
            end

            out = d;
        end
    end
endmodule

verilog/task5/q6/alu_test.v
`timescale 1ns/1ps
module alu_test;

reg [39:0]a,b;
reg clk;
reg [4:0]s;
wire [39:0]out;

alu uut (.a(a), .b(b), .s(s), .clk(clk), .out(out));

initial begin
$dumpfile("alua.vcd");
$dumpvars(0, alu_test);
a= 40'h000000000b;
b= 40'h0000000003;
clk=0;
s= 5'b00101;
end

always
begin
#3 clk=~clk;
end

initial
begin
#10 s = 5'b00111;
#10 s = 5'b00110;
#10 s = 5'b01000;
#10 s = 5'b01011;
#10 s = 5'b01100;
#10 s = 5'b10100;
$finish;
end


endmodule

verilog/task5/q6/alua.vcd
$date
	Tue Jul 18 11:40:41 2023
$end
$version
	Icarus Verilog
$end
$timescale
	1ps
$end
$scope module alu_test $end
$var wire 40 ! out [39:0] $end
$var reg 40 " a [39:0] $end
$var reg 40 # b [39:0] $end
$var reg 1 $ clk $end
$var reg 5 % s [4:0] $end
$scope module uut $end
$var wire 40 & a [39:0] $end
$var wire 40 ' b [39:0] $end
$var wire 1 $ clk $end
$var wire 5 ( s [4:0] $end
$var reg 40 ) c [39:0] $end
$var reg 40 * d [39:0] $end
$var reg 1 + i $end
$var reg 40 , out [39:0] $end
$upscope $end
$upscope $end
$enddefinitions $end
#0
$dumpvars
bx ,
x+
bx *
bx )
b111 (
b11 '
b1011 &
b111 %
0$
b11 #
b1011 "
bx !
$end
#3000
b1110 !
b1110 ,
1$
#6000
0$
#9000
1$
#10000
b110 %
b110 (
#12000
0$
#15000
b1000 !
b1000 ,
1$
#18000
0$
#20000
b1000 %
b1000 (
#21000
b100001 !
b100001 ,
1$
#24000
0$
#27000
1$
#30000
0$
b1011 %
b1011 (
#33000
b11 !
b11 ,
1$
#36000
0$
#39000
1$
#40000
b1100 %
b1100 (
#42000
0$
#45000
b11 !
b11 +
1$
#48000
0$
#50000
b1100 %
b1100 (
#51000
b101100 !
b101100 +
b101100 *
b100110 ,
1$
#54000
0$
#57000
b100110 ,
1$
#60000
0$
b10100 %
b10100 (
