verilog/task2/subtask1/synchronous_reset/dff.v
/*Important: Once you run ./a.out, it will keep running infinitely, because it is in an always block. You need to hit Ctrl +Z to stop it, else, the vcd will become a large file and will never end.

*/

`timescale 1ns/1ps

module dflipflop(q, d, clk, rst);
output q;
input d;
input rst;
input clk;
reg q;

//behavioral/ sequential designs

always @(posedge clk) // sensitivity list
begin 
if(rst)
q=0;
else
q = d;  // <= is a non-blocking statement
end
endmodule

//Testbench:

verilog/task2/subtask1/synchronous_reset/dflipfloptb.v
module dflipfloptb;

reg d;

reg clk;

wire q;
reg rst;

dflipflop uut (q,d,clk,rst);

initial begin

// Initialize Inputs

$dumpfile ("dff_out.vcd"); 
$dumpvars(0,dflipfloptb);

//These initial statements are very important- without which the next always block
//will not work

d = 0;  //at time=0
clk = 0; //at time=0
rst = 1;
#5
rst = 0;
#5
rst = 1;
#6
rst = 0;
end

always 
#3 clk=~clk; // toggle or negate the clock every 3 units of time.
// ~ is a negation operator

always 
#5 d=~d;  // toggle or negate the D input every 5 units of time
//Alternately:
//always begin
//#5 d =1;
//#15 d=0;
//end

endmodule

verilog/task2/subtask1/synchronous_reset/dff_out.vcd
$date
	Thu Jul 13 18:39:48 2023
$end
$version
	Icarus Verilog
$end
$timescale
	1ps
$end
$scope module dflipfloptb $end
$var wire 1 ! q $end
$var reg 1 " clk $end
$var reg 1 # d $end
$var reg 1 $ rst $end
$scope module uut $end
$var wire 1 " clk $end
$var wire 1 # d $end
$var wire 1 $ rst $end
$var reg 1 ! q $end
$upscope $end
$upscope $end
$enddefinitions $end
#0
$dumpvars
1$
0#
0"
x!
$end
#3000
0!
1"
#5000
1#
0$
#6000
0"
#9000
1!
1"
#10000
0#
1$
#12000
0"
#15000
0!
1"
1#
#16000
0$
#18000
0"
#20000
0#
#21000
1"
#24000
0"
#25000
1#
#27000
1!
1"
#30000
0"
0#
#33000
0!
1"
#35000
1#
#36000
0"
#39000
1!
1"
#40000
0#
#42000
0"
#45000
1"
1#
#48000
0"
#50000
0#
#51000
0!
1"
#54000
0"
#55000
1#
#57000
1!
1"
#60000
0"
0#
#63000
0!
1"
#65000
1#
#66000
0"
#69000
1!
1"
#70000
0#
#72000
0"
#75000
1"
1#
#78000
0"
#80000
0#
#81000
0!
1"
#84000
0"
#85000
1#
#87000
1!
1"
#90000
0"
0#
#93000
0!
1"
#95000
1#
#96000
0"
#99000
1!
1"
#100000
0#
#102000
0"
#105000
1"
1#
#108000
0"
#110000
0#
#111000
0!
1"
#114000
0"
#115000
1#
#117000
1!
1"
#120000
0"
0#
#123000
0!
1"
#125000
1#
#126000
0"
#129000
1!
1"
#130000
0#
#132000
0"
#135000
1"
1#
#138000
0"
#140000
0#
#141000
0!
1"
#144000
0"
#145000
1#
#147000
1!
1"
#150000
0"
0#
#153000
0!
1"
#155000
1#
#156000
0"
#159000
1!
1"
#160000
0#
#162000
0"
#165000
1"
1#
#168000
0"
#170000
0#
#171000
0!
1"
#174000
0"
#175000
1#
#177000
1!
1"
#180000
0"
0#
#183000
0!
1"
#185000
1#
#186000
0"
#189000
1!
1"
#190000
0#
#192000
0"
#195000
1"
1#
#198000
0"
#200000
0#
#201000
0!
1"
#204000
0"
#205000
1#
#207000
1!
1"
#210000
0"
0#
#213000
0!
1"
#215000
1#
#216000
0"
#219000
1!
1"
#220000
0#
#222000
0"
#225000
1"
1#
#228000
0"
#230000
0#
#231000
0!
1"
#234000
0"
#235000
1#
#237000
1!
1"
#240000
0"
0#
#243000
0!
1"
#245000
1#
#246000
0"
#249000
1!
1"
#250000
0#
#252000
0"
#255000
1"
1#
#258000
0"
#260000
0#
#261000
0!
1"
#264000
0"
#265000
1#
#267000
1!
1"
#270000
0"
0#
#273000
0!
1"
#275000
1#
#276000
0"
#279000
1!
1"
#280000
0#
#282000
0"
#285000
1"
1#
#288000
0"
#290000
0#
#291000
0!
1"
#294000
0"
#295000
1#
#297000
1!
1"
#300000
0"
0#
#303000
0!
1"
#305000
1#
#306000
0"
#309000
1!
1"
#310000
0#
#312000
0"
#315000
1"
1#
#318000
0"
#320000
0#
#321000
0!
1"
#324000
0"
#325000
1#
#327000
1!
1"
#330000
0"
0#
#333000
0!
1"
#335000
1#
#336000
0"
#339000
1!
1"
#340000
0#
#342000
0"
#345000
1"
1#
#348000
0"
#350000
0#
#351000
0!
1"
#354000
0"
#355000
1#
#357000
1!
1"
#360000
0"
0#
#363000
0!
1"
#365000
1#
#366000
0"
#369000
1!
1"
#370000
0#
#372000
0"
#375000
1"
1#
#378000
0"
#380000
0#
#381000
0!
1"
#384000
0"
#385000
1#
#387000
1!
1"
#390000
0"
0#
#393000
0!
1"
#395000
1#
#396000
0"
#399000
1!
1"
#400000
0#
#402000
0"
#405000
1"
1#
#408000
0"
#410000
0#
#411000
0!
1"
#414000
0"
#415000
1#
#417000
1!
1"
#420000
0"
0#
#423000
0!
1"
#425000
1#
#426000
0"
#429000
1!
1"
#430000
0#
#432000
0"
#435000
1"
1#
#438000
0"
#440000
0#
#441000
0!
1"
#444000
0"
#445000
1#
#447000
1!
1"
#450000
0"
0#
#453000
0!
1"
#455000
1#
#456000
0"
#459000
1!
1"
#460000
0#
#462000
0"
#465000
1"
1#
#468000
0"
#470000
0#
#471000
0!
1"
#474000
0"
#475000
1#
#477000
1!
1"
#480000
0"
0#
#483000
0!
1"
#485000
1#
#486000
0"
#489000
1!
1"
#490000
0#
#492000
0"
#495000
1"
1#
#498000
0"
#500000
0#
#501000
0!
1"
#504000
0"
#505000
1#
#507000
1!
1"
#510000
0"
0#
#513000
0!
1"
#515000
1#
#516000
0"
#519000
1!
1"
#520000
0#
#522000
0"
#525000
1"
1#
#528000
0"
#530000
0#
#531000
0!
1"
#534000
0"
#535000
1#
#537000
1!
1"
#540000
0"
0#
#543000
0!
1"
#545000
1#
#546000
0"
#549000
1!
1"
#550000
0#
#552000
0"
#555000
1"
1#
#558000
0"
#560000
0#
#561000
0!
1"
#564000
0"
#565000
1#
#567000
1!
1"
#570000
0"
0#
#573000
0!
1"
#575000
1#
#576000
0"
#579000
1!
1"
#580000
0#
#582000
0"
#585000
1"
1#
#588000
0"
#590000
0#
#591000
0!
1"
#594000
0"
#595000
1#
#597000
1!
1"
#600000
0"
0#
#603000
0!
1"
#605000
1#
#606000
0"
#609000
1!
1"
#610000
0#
#612000
0"
#615000
1"
1#
#618000
0"
#620000
0#
#621000
0!
1"
#624000
0"
#625000
1#
#627000
1!
1"
#630000
0"
0#
#633000
0!
1"
#635000
1#
#636000
0"
#639000
1!
1"
#640000
0#
#642000
0"
#645000
1"
1#
#648000
0"
#650000
0#
#651000
0!
1"
#654000
0"
#655000
1#
#657000
1!
1"
#660000
0"
0#
#663000
0!
1"
#665000
1#
#666000
0"
#669000
1!
1"
#670000
0#
#672000
0"
#675000
1"
1#
#678000
0"
#680000
0#
#681000
0!
1"
#684000
0"
#685000
1#
#687000
1!
1"
#690000
0"
0#
#693000
0!
1"
#695000
1#
#696000
0"
#699000
1!
1"
#700000
0#
#702000
0"
#705000
1"
1#
#708000
0"
#710000
0#
#711000
0!
1"
#714000
0"
#715000
1#
#717000
1!
1"
#720000
0"
0#
#723000
0!
1"
#725000
1#
#726000
0"
#729000
1!
1"
#730000
0#
#732000
0"
#735000
1"
1#
#738000
0"
#740000
0#
#741000
0!
1"
#744000
0"
#745000
1#
#747000
1!
1"
#750000
0"
0#
#753000
0!
1"
#755000
1#
#756000
0"
#759000
1!
1"
#760000
0#
#762000
0"
#765000
1"
1#
#768000
0"
#770000
0#
#771000
0!
1"
#774000
0"
#775000
1#
#777000
1!
1"
#780000
0"
0#
#783000
0!
1"
#785000
1#
#786000
0"
#789000
1!
1"
#790000
0#
#792000
0"
#795000
1"
1#
#798000
0"
#800000
0#
#801000
0!
1"
#804000
0"
#805000
1#
#807000
1!
1"
#810000
0"
0#
#813000
0!
1"
#815000
1#
#816000
0"
#819000
1!
1"
#820000
0#
#822000
0"
#825000
1"
1#
#828000
0"
#830000
0#
#831000
0!
1"
#834000
0"
#835000
1#
#837000
1!
1"
#840000
0"
0#
#843000
0!
1"
#845000
1#
#846000
0"
#849000
1!
1"
#850000
0#
#852000
0"
#855000
1"
1#
#858000
0"
#860000
0#
#861000
0!
1"
#864000
0"
#865000
1#
#867000
1!
1"
#870000
0"
0#
#873000
0!
1"
#875000
1#
#876000
0"
#879000
1!
1"
#880000
0#
#882000
0"
#885000
1"
1#
#888000
0"
#890000
0#
#891000
0!
1"
#894000
0"
#895000
1#
#897000
1!
1"
#900000
0"
0#
#903000
0!
1"
#905000
1#
#906000
0"
#909000
1!
1"
#910000
0#
#912000
0"
#915000
1"
1#
#918000
0"
#920000
0#
#921000
0!
1"
#924000
0"
#925000
1#
#927000
1!
1"
#930000
0"
0#
#933000
0!
1"
#935000
1#
#936000
0"
#939000
1!
1"
#940000
0#
#942000
0"
#945000
1"
1#
#948000
0"
#950000
0#
#951000
0!
1"
#954000
0"
#955000
1#
#957000
1!
1"
#960000
0"
0#
#963000
0!
1"
#965000
1#
#966000
0"
#969000
1!
1"
#970000
0#
#972000
0"
#975000
1"
1#
#978000
0"
#980000
0#
#981000
0!
1"
#984000
0"
#985000
1#
#987000
1!
1"
#990000
0"
0#
#993000
0!
1"
#995000
1#
#996000
0"
#999000
1!
1"
#1000000
0#
#1002000
0"
#1005000
1"
1#
#1008000
0"
#1010000
0#
#1011000
0!
1"
#1014000
0"
#1015000
1#
#1017000
1!
1"
#1020000
0"
0#
#1023000
0!
1"
#1025000
1#
#1026000
0"
#1029000
1!
1"
#1030000
0#
#1032000
0"
#1035000
1"
1#
#1038000
0"
#1040000
0#
#1041000
0!
1"
#1044000
0"
#1045000
1#
#1047000
1!
1"
#1050000
0"
0#
#1053000
0!
1"
#1055000
1#
#1056000
0"
#1059000
1!
1"
#1060000
0#
#1062000
0"
#1065000
1"
1#
#1068000
0"
#1070000
0#
#1071000
0!
1"
#1074000
0"
#1075000
1#
#1077000
1!
1"
#1080000
0"
0#
#1083000
0!
1"
#1085000
1#
#1086000
0"
#1089000
1!
1"
#1090000
0#
#1092000
0"
#1095000
1"
1#
#1098000
0"
#1100000
0#
#1101000
0!
1"
#1104000
0"
#1105000
1#
#1107000
1!
1"
#1110000
0"
0#
#1113000
0!
1"
#1115000
1#
#1116000
0"
#1119000
1!
1"
#1120000
0#
#1122000
0"
#1125000
1"
1#
#1128000
0"
#1130000
0#
#1131000
0!
1"
#1134000
0"
#1135000
1#
#1137000
1!
1"
#1140000
0"
0#
#1143000
0!
1"
#1145000
1#
#1146000
0"
#1149000
1!
1"
#1150000
0#
#1152000
0"
#1155000
1"
1#
#1158000
0"
#1160000
0#
#1161000
0!
1"
#1164000
0"
#1165000
1#
#1167000
1!
1"
#1170000
0"
0#
#1173000
0!
1"
#1175000
1#
#1176000
0"
#1179000
1!
1"
#1180000
0#
#1182000
0"
#1185000
1"
1#
#1188000
0"
#1190000
0#
#1191000
0!
1"
#1194000
0"
#1195000
1#
#1197000
1!
1"
#1200000
0"
0#
#1203000
0!
1"
#1205000
1#
#1206000
0"
#1209000
1!
1"
#1210000
0#
#1212000
0"
#1215000
1"
1#
#1218000
0"
#1220000
0#
#1221000
0!
1"
#1224000
0"
#1225000
1#
#1227000
1!
1"
#1230000
0"
0#
#1233000
0!
1"
#1235000
1#
#1236000
0"
#1239000
1!
1"
#1240000
0#
#1242000
0"
#1245000
1"
1#
#1248000
0"
#1250000
0#
#1251000
0!
1"
#1254000
0"
#1255000
1#
#1257000
1!
1"
#1260000
0"
0#
#1263000
0!
1"
#1265000
1#
#1266000
0"
#1269000
1!
1"
#1270000
0#
#1272000
0"
#1275000
1"
1#
#1278000
0"
#1280000
0#
#1281000
0!
1"
#1284000
0"
#1285000
1#
#1287000
1!
1"
#1290000
0"
0#
#1293000
0!
1"
#1295000
1#
#1296000
0"
#1299000
1!
1"
#1300000
0#
#1302000
0"
#1305000
1"
1#
#1308000
0"
#1310000
0#
#1311000
0!
1"
#1314000
0"
#1315000
1#
#1317000
1!
1"
#1320000
0"
0#
#1323000
0!
1"
#1325000
1#
#1326000
0"
#1329000
1!
1"
#1330000
0#
#1332000
0"
#1335000
1"
1#
#1338000
0"
#1340000
0#
#1341000
0!
1"
#1344000
0"
#1345000
1#
#1347000
1!
1"
#1350000
0"
0#
#1353000
0!
1"
#1355000
1#
#1356000
0"
#1359000
1!
1"
#1360000
0#
#1362000
0"
#1365000
1"
1#
#1368000
0"
#1370000
0#
#1371000
0!
1"
#1374000
0"
#1375000
1#
#1377000
1!
1"
#1380000
0"
0#
#1383000
0!
1"
#1385000
1#
#1386000
0"
#1389000
1!
1"
#1390000
0#
#1392000
0"
#1395000
1"
1#
#1398000
0"
#1400000
0#
#1401000
0!
1"
#1404000
0"
#1405000
1#
#1407000
1!
1"
#1410000
0"
0#
#1413000
0!
1"
#1415000
1#
#1416000
0"
#1419000
1!
1"
#1420000
0#
#1422000
0"
#1425000
1"
1#
#1428000
0"
#1430000
0#
#1431000
0!
1"
#1434000
0"
#1435000
1#
#1437000
1!
1"
#1440000
0"
0#
#1443000
0!
1"
#1445000
1#
#1446000
0"
#1449000
1!
1"
#1450000
0#
#1452000
0"
#1455000
1"
1#
#1458000
0"
#1460000
0#
#1461000
0!
1"
#1464000
0"
#1465000
1#
#1467000
1!
1"
#1470000
0"
0#
#1473000
0!
1"
#1475000
1#
#1476000
0"
#1479000
1!
1"
#1480000
0#
#1482000
0"
#1485000
1"
1#
#1488000
0"
#1490000
0#
#1491000
0!
1"
#1494000
0"
#1495000
1#
#1497000
1!
1"
#1500000
0"
0#
#1503000
0!
1"
#1505000
1#
#1506000
0"
#1509000
1!
1"
#1510000
0#
#1512000
0"
#1515000
1"
1#
#1518000
0"
#1520000
0#
#1521000
0!
1"
#1524000
0"
#1525000
1#
#1527000
1!
1"
#1530000
0"
0#
#1533000
0!
1"
#1535000
1#
#1536000
0"
#1539000
1!
1"
#1540000
0#
#1542000
0"
#1545000
1"
1#
#1548000
0"
#1550000
0#
#1551000
0!
1"
#1554000
0"
#1555000
1#
#1557000
1!
1"
#1560000
0"
0#
#1563000
0!
1"
#1565000
1#
#1566000
0"
#1569000
1!
1"
#1570000
0#
#1572000
0"
#1575000
1"
1#
#1578000
0"
#1580000
0#
#1581000
0!
1"
#1584000
0"
#1585000
1#
#1587000
1!
1"
#1590000
0"
0#
#1593000
0!
1"
#1595000
1#
#1596000
0"
#1599000
1!
1"
#1600000
0#
#1602000
0"
#1605000
1"
1#
#1608000
0"
#1610000
0#
#1611000
0!
1"
#1614000
0"
#1615000
1#
#1617000
1!
1"
#1620000
0"
0#
#1623000
0!
1"
#1625000
1#
#1626000
0"
#1629000
1!
1"
#1630000
0#
#1632000
0"
#1635000
1"
1#
#1638000
0"
#1640000
0#
#1641000
0!
1"
#1644000
0"
#1645000
1#
#1647000
1!
1"
#1650000
0"
0#
#1653000
0!
1"
#1655000
1#
#1656000
0"
#1659000
1!
1"
#1660000
0#
#1662000
0"
#1665000
1"
1#
#1668000
0"
#1670000
0#
#1671000
0!
1"
#1674000
0"
#1675000
1#
#1677000
1!
1"
#1680000
0"
0#
#1683000
0!
1"
#1685000
1#
#1686000
0"
#1689000
1!
1"
#1690000
0#
#1692000
0"
#1695000
1"
1#
#1698000
0"
#1700000
0#
#1701000
0!
1"
#1704000
0"
#1705000
1#
#1707000
1!
1"
#1710000
0"
0#
#1713000
0!
1"
#1715000
1#
#1716000
0"
#1719000
1!
1"
#1720000
0#
#1722000
0"
#1725000
1"
1#
#1728000
0"
#1730000
0#
#1731000
0!
1"
#1734000
0"
#1735000
1#
#1737000
1!
1"
#1740000
0"
0#
#1743000
0!
1"
#1745000
1#
#1746000
0"
#1749000
1!
1"
#1750000
0#
#1752000
0"
#1755000
1"
1#
#1758000
0"
#1760000
0#
#1761000
0!
1"
#1764000
0"
#1765000
1#
#1767000
1!
1"
#1770000
0"
0#
#1773000
0!
1"
#1775000
1#
#1776000
0"
#1779000
1!
1"
#1780000
0#
#1782000
0"
#1785000
1"
1#
#1788000
0"
#1790000
0#
#1791000
0!
1"
#1794000
0"
#1795000
1#
#1797000
1!
1"
#1800000
0"
0#
#1803000
0!
1"
#1805000
1#
#1806000
0"
#1809000
1!
1"
#1810000
0#
#1812000
0"
#1815000
1"
1#
#1818000
0"
#1820000
0#
#1821000
0!
1"
#1824000
0"
#1825000
1#
#1827000
1!
1"
#1830000
0"
0#
#1833000
0!
1"
#1835000
1#
#1836000
0"
#1839000
1!
1"
#1840000
0#
#1842000
0"
#1845000
1"
1#
#1848000
0"
#1850000
0#
#1851000
0!
1"
#1854000
0"
#1855000
1#
#1857000
1!
1"
#1860000
0"
0#
#1863000
0!
1"
#1865000
1#
#1866000
0"
#1869000
1!
1"
#1870000
0#
#1872000
0"
#1875000
1"
1#
#1878000
0"
#1880000
0#
#1881000
0!
1"
#1884000
0"
#1885000
1#
#1887000
1!
1"
#1890000
0"
0#
#1893000
0!
1"
#1895000
1#
#1896000
0"
#1899000
1!
1"
#1900000
0#
#1902000
0"
#1905000
1"
1#
#1908000
0"
#1910000
0#
#1911000
0!
1"
#1914000
0"
#1915000
1#
#1917000
1!
1"
#1920000
0"
0#
#1923000
0!
1"
#1925000
1#
#1926000
0"
#1929000
1!
1"
#1930000
0#
#1932000
0"
#1935000
1"
1#
#1938000
0"
#1940000
0#
#1941000
0!
1"
#1944000
0"
#1945000
1#
#1947000
1!
1"
#1950000
0"
0#
#1953000
0!
1"
#1955000
1#
#1956000
0"
#1959000
1!
1"
#1960000
0#
#1962000
0"
#1965000
1"
1#
#1968000
0"
#1970000
0#
#1971000
0!
1"
#1974000
0"
#1975000
1#
#1977000
1!
1"
#1980000
0"
0#
#1983000
0!
1"
#1985000
1#
#1986000
0"
#1989000
1!
1"
#1990000
0#
#1992000
0"
#1995000
1"
1#
#1998000
0"
#2000000
0#
#2001000
0!
1"
#2004000
0"
#2005000
1#
#2007000
1!
1"
#2010000
0"
0#
#2013000
0!
1"
#2015000
1#
#2016000
0"
#2019000
1!
1"
#2020000
0#
#2022000
0"
#2025000
1"
1#
#2028000
0"
#2030000
0#
#2031000
0!
1"
#2034000
0"
#2035000
1#
#2037000
1!
1"
#2040000
0"
0#
#2043000
0!
1"
#2045000
1#
#2046000
0"
#2049000
1!
1"
#2050000
0#
#2052000
0"
#2055000
1"
1#
#2058000
0"
#2060000
0#
#2061000
0!
1"
#2064000
0"
#2065000
1#
#2067000
1!
1"
#2070000
0"
0#
#2073000
0!
1"
#2075000
1#
#2076000
0"
#2079000
1!
1"
#2080000
0#
#2082000
0"
#2085000
1"
1#
#2088000
0"
#2090000
0#
#2091000
0!
1"
#2094000
0"
#2095000
1#
#2097000
1!
1"
#2100000
0"
0#
#2103000
0!
1"
#2105000
1#
#2106000
0"
#2109000
1!
1"
#2110000
0#
#2112000
0"
#2115000
1"
1#
#2118000
0"
#2120000
0#
#2121000
0!
1"
#2124000
0"
#2125000
1#
#2127000
1!
1"
#2130000
0"
0#
#2133000
0!
1"
#2135000
1#
#2136000
0"
#2139000
1!
1"
#2140000
0#
#2142000
0"
#2145000
1"
1#
#2148000
0"
#2150000
0#
#2151000
0!
1"
#2154000
0"
#2155000
1#
#2157000
1!
1"
#2160000
0"
0#
#2163000
0!
1"
#2165000
1#
#2166000
0"
#2169000
1!
1"
#2170000
0#
#2172000
0"
#2175000
1"
1#
#2178000
0"
#2180000
0#
#2181000
0!
1"
#2184000
0"
#2185000
1#
#2187000
1!
1"
#2190000
0"
0#
#2193000
0!
1"
#2195000
1#
#2196000
0"
#2199000
1!
1"
#2200000
0#
#2202000
0"
#2205000
1"
1#
#2208000
0"
#2210000
0#
#2211000
0!
1"
#2214000
0"
#2215000
1#
#2217000
1!
1"
#2220000
0"
0#
#2223000
0!
1"
#2225000
1#
#2226000
0"
#2229000
1!
1"
#2230000
0#
#2232000
0"
#2235000
1"
1#
#2238000
0"
#2240000
0#
#2241000
0!
1"
#2244000
0"
#2245000
1#
#2247000
1!
1"
#2250000
0"
0#
#2253000
0!
1"
#2255000
1#
#2256000
0"
#2259000
1!
1"
#2260000
0#
#2262000
0"
#2265000
1"
1#
#2268000
0"
#2270000
0#
#2271000
0!
1"
#2274000
0"
#2275000
1#
#2277000
1!
1"
#2280000
0"
0#
#2283000
0!
1"
#2285000
1#
#2286000
0"
#2289000
1!
1"
#2290000
0#
#2292000
0"
#2295000
1"
1#
#2298000
0"
#2300000
0#
#2301000
0!
1"
#2304000
0"
#2305000
1#
#2307000
1!
1"
#2310000
0"
0#
#2313000
0!
1"
#2315000
1#
#2316000
0"
#2319000
1!
1"
#2320000
0#
#2322000
0"
#2325000
1"
1#
#2328000
0"
#2330000
0#
#2331000
0!
1"
#2334000
0"
#2335000
1#
#2337000
1!
1"
#2340000
0"
0#
#2343000
0!
1"
#2345000
1#
#2346000
0"
#2349000
1!
1"
#2350000
0#
#2352000
0"
#2355000
1"
1#
#2358000
0"
#2360000
0#
#2361000
0!
1"
#2364000
0"
#2365000
1#
#2367000
1!
1"
#2370000
0"
0#
#2373000
0!
1"
#2375000
1#
#2376000
0"
#2379000
1!
1"
#2380000
0#
#2382000
0"
#2385000
1"
1#
#2388000
0"
#2390000
0#
#2391000
0!
1"
#2394000
0"
#2395000
1#
#2397000
1!
1"
#2400000
0"
0#
#2403000
0!
1"
#2405000
1#
#2406000
0"
#2409000
1!
1"
#2410000
0#
#2412000
0"
#2415000
1"
1#
#2418000
0"
#2420000
0#
#2421000
0!
1"
#2424000
0"
#2425000
1#
#2427000
1!
1"
#2430000
0"
0#
#2433000
0!
1"
#2435000
1#
#2436000
0"
#2439000
1!
1"
#2440000
0#
#2442000
0"
#2445000
1"
1#
#2448000
0"
#2450000
0#
#2451000
0!
1"
#2454000
0"
#2455000
1#
#2457000
1!
1"
#2460000
0"
0#
#2463000
0!
1"
#2465000
1#
#2466000
0"
#2469000
1!
1"
#2470000
0#
#2472000
0"
#2475000
1"
1#
#2478000
0"
#2480000
0#
#2481000
0!
1"
#2484000
0"
#2485000
1#
#2487000
1!
1"
#2490000
0"
0#
#2493000
0!
1"
#2495000
1#
#2496000
0"
#2499000
1!
1"
#2500000
0#
#2502000
0"
#2505000
1"
1#
#2508000
0"
#2510000
0#
#2511000
0!
1"
#2514000
0"
#2515000
1#
#2517000
1!
1"
#2520000
0"
0#
#2523000
0!
1"
#2525000
1#
#2526000
0"
#2529000
1!
1"
#2530000
0#
#2532000
0"
#2535000
1"
1#
#2538000
0"
#2540000
0#
#2541000
0!
1"
#2544000
0"
#2545000
1#
#2547000
1!
1"
#2550000
0"
0#
#2553000
0!
1"
#2555000
1#
#2556000
0"
#2559000
1!
1"
#2560000
0#
#2562000
0"
#2565000
1"
1#
#2568000
0"
#2570000
0#
#2571000
0!
1"
#2574000
0"
#2575000
1#
#2577000
1!
1"
#2580000
0"
0#
#2583000
0!
1"
#2585000
1#
#2586000
0"
#2589000
1!
1"
#2590000
0#
#2592000
0"
#2595000
1"
1#
#2598000
0"
#2600000
0#
#2601000
0!
1"
#2604000
0"
#2605000
1#
#2607000
1!
1"
#2610000
0"
0#
#2613000
0!
1"
#2615000
1#
#2616000
0"
#2619000
1!
1"
#2620000
0#
#2622000
0"
#2625000
1"
1#
#2628000
0"
#2630000
0#
#2631000
0!
1"
#2634000
0"
#2635000
1#
#2637000
1!
1"
#2640000
0"
0#
#2643000
0!
1"
#2645000
1#
#2646000
0"
#2649000
1!
1"
#2650000
0#
#2652000
0"
#2655000
1"
1#
#2658000
0"
#2660000
0#
#2661000
0!
1"
#2664000
0"
#2665000
1#
#2667000
1!
1"
#2670000
0"
0#
#2673000
0!
1"
#2675000
1#
#2676000
0"
#2679000
1!
1"
#2680000
0#
#2682000
0"
#2685000
1"
1#
#2688000
0"
#2690000
0#
#2691000
0!
1"
#2694000
0"
#2695000
1#
#2697000
1!
1"
#2700000
0"
0#
#2703000
0!
1"
#2705000
1#
#2706000
0"
#2709000
1!
1"
#2710000
0#
#2712000
0"
#2715000
1"
1#
#2718000
0"
#2720000
0#
#2721000
0!
1"
#2724000
0"
#2725000
1#
#2727000
1!
1"
#2730000
0"
0#
#2733000
0!
1"
#2735000
1#
#2736000
0"
#2739000
1!
1"
#2740000
0#
#2742000
0"
#2745000
1"
1#
#2748000
0"
#2750000
0#
#2751000
0!
1"
#2754000
0"
#2755000
1#
#2757000
1!
1"
#2760000
0"
0#
#2763000
0!
1"
#2765000
1#
#2766000
0"
#2769000
1!
1"
#2770000
0#
#2772000
0"
#2775000
1"
1#
#2778000
0"
#2780000
0#
#2781000
0!
1"
#2784000
0"
#2785000
1#
#2787000
1!
1"
#2790000
0"
0#
#2793000
0!
1"
#2795000
1#
#2796000
0"
#2799000
1!
1"
#2800000
0#
#2802000
0"
#2805000
1"
1#
#2808000
0"
#2810000
0#
#2811000
0!
1"
#2814000
0"
#2815000
1#
#2817000
1!
1"
#2820000
0"
0#
#2823000
0!
1"
#2825000
1#
#2826000
0"
#2829000
1!
1"
#2830000
0#
#2832000
0"
#2835000
1"
1#
#2838000
0"
#2840000
0#
#2841000
0!
1"
#2844000
0"
#2845000
1#
#2847000
1!
1"
#2850000
0"
0#
#2853000
0!
1"
#2855000
1#
#2856000
0"
#2859000
1!
1"
#2860000
0#
#2862000
0"
#2865000
1"
1#
#2868000
0"
#2870000
0#
#2871000
0!
1"
#2874000
0"
#2875000
1#
#2877000
1!
1"
#2880000
0"
0#
#2883000
0!
1"
#2885000
1#
#2886000
0"
#2889000
1!
1"
#2890000
0#
#2892000
0"
#2895000
1"
1#
#2898000
0"
#2900000
0#
#2901000
0!
1"
#2904000
0"
#2905000
1#
#2907000
1!
1"
#2910000
0"
0#
#2913000
0!
1"
#2915000
1#
#2916000
0"
#2919000
1!
1"
#2920000
0#
#2922000
0"
#2925000
1"
1#
#2928000
0"
#2930000
0#
#2931000
0!
1"
#2934000
0"
#2935000
1#
#2937000
1!
1"
#2940000
0"
0#
#2943000
0!
1"
#2945000
1#
#2946000
0"
#2949000
1!
1"
#2950000
0#
#2952000
0"
#2955000
1"
1#
#2958000
0"
#2960000
0#
#2961000
0!
1"
#2964000
0"
#2965000
1#
#2967000
1!
1"
#2970000
0"
0#
#2973000
0!
1"
#2975000
1#
#2976000
0"
#2979000
1!
1"
#2980000
0#
#2982000
0"
#2985000
1"
1#
#2988000
0"
#2990000
0#
#2991000
0!
1"
#2994000
0"
#2995000
1#
#2997000
1!
1"
#3000000
0"
0#
#3003000
0!
1"
#3005000
1#
#3006000
0"
#3009000
1!
1"
#3010000
0#
#3012000
0"
#3015000
1"
1#
#3018000
0"
#3020000
0#
#3021000
0!
1"
#3024000
0"
#3025000
1#
#3027000
1!
1"
#3030000
0"
0#
#3033000
0!
1"
#3035000
1#
#3036000
0"
#3039000
1!
1"
#3040000
0#
#3042000
0"
#3045000
1"
1#
#3048000
0"
#3050000
0#
#3051000
0!
1"
#3054000
0"
#3055000
1#
#3057000
1!
1"
#3060000
0"
0#
#3063000
0!
1"
#3065000
1#
#3066000
0"
#3069000
1!
1"
#3070000
0#
#3072000
0"
#3075000
1"
1#
#3078000
0"
#3080000
0#
#3081000
0!
1"
#3084000
0"
#3085000
1#
#3087000
1!
1"
#3090000
0"
0#
#3093000
0!
1"
#3095000
1#
#3096000
0"
#3099000
1!
1"
#3100000
0#
#3102000
0"
#3105000
1"
1#
#3108000
0"
#3110000
0#
#3111000
0!
1"
#3114000
0"
#3115000
1#
#3117000
1!
1"
#3120000
0"
0#
#3123000
0!
1"
#3125000
1#
#3126000
0"
#3129000
1!
1"
#3130000
0#
#3132000
0"
#3135000
1"
1#
#3138000
0"
#3140000
0#
#3141000
0!
1"
#3144000
0"
#3145000
1#
#3147000
1!
1"
#3150000
0"
0#
#3153000
0!
1"
#3155000
1#
#3156000
0"
#3159000
1!
1"
#3160000
0#
#3162000
0"
#3165000
1"
1#
#3168000
0"
#3170000
0#
#3171000
0!
1"
#3174000
0"
#3175000
1#
#3177000
1!
1"
#3180000
0"
0#
#3183000
0!
1"
#3185000
1#
#3186000
0"
#3189000
1!
1"
#3190000
0#
#3192000
0"
#3195000
1"
1#
#3198000
0"
#3200000
0#
#3201000
0!
1"
#3204000
0"
#3205000
1#
#3207000
1!
1"
#3210000
0"
0#
#3213000
0!
1"
#3215000
1#
#3216000
0"
#3219000
1!
1"
#3220000
0#
#3222000
0"
#3225000
1"
1#
#3228000
0"
#3230000
0#
#3231000
0!
1"
#3234000
0"
#3235000
1#
#3237000
1!
1"
#3240000
0"
0#
#3243000
0!
1"
#3245000
1#
#3246000
0"
#3249000
1!
1"
#3250000
0#
#3252000
0"
#3255000
1"
1#
#3258000
0"
#3260000
0#
#3261000
0!
1"
#3264000
0"
#3265000
1#
#3267000
1!
1"
#3270000
0"
0#
#3273000
0!
1"
#3275000
1#
#3276000
0"
#3279000
1!
1"
#3280000
0#
#3282000
0"
#3285000
1"
1#
#3288000
0"
#3290000
0#
#3291000
0!
1"
#3294000
0"
#3295000
1#
#3297000
1!
1"
#3300000
0"
0#
#3303000
0!
1"
#3305000
1#
#3306000
0"
#3309000
1!
1"
#3310000
0#
#3312000
0"
#3315000
1"
1#
#3318000
0"
#3320000
0#
#3321000
0!
1"
#3324000
0"
#3325000
1#
#3327000
1!
1"
#3330000
0"
0#
#3333000
0!
1"
#3335000
1#
#3336000
0"
#3339000
1!
1"
#3340000
0#
#3342000
0"
#3345000
1"
1#
#3348000
0"
#3350000
0#
#3351000
0!
1"
#3354000
0"
#3355000
1#
#3357000
1!
1"
#3360000
0"
0#
#3363000
0!
1"
#3365000
1#
#3366000
0"
#3369000
1!
1"
#3370000
0#
#3372000
0"
#3375000
1"
1#
#3378000
0"
