verilog/task1/subtask4/full_adder.v

module full_Adder( 
  input D1, D2, Cin, 
  output Sum_out, Cout
  );  
    wire a1, a2, a3;    

xor u1(a1,D1,D2);
and u2(a2,D1,D2);
and u3(a3,a1,Cin);
or u4(Cout,a2,a3);
xor u5(Sum_out,a1,Cin); 

endmodule

verilog/task1/subtask4/rca4.v
`include "full_adder.v"

module rca4(
    input [3:0]a,b,
    input cin,
    output [3:0]sum,
    output cout
);
wire [2:0]c;

full_Adder M0(.D1(a[0]), .D2(b[0]), .Cin(cin), .Sum_out(sum[0]), .Cout(c[0]));
full_Adder M1(.D1(a[1]), .D2(b[1]), .Cin(c[0]), .Sum_out(sum[1]), .Cout(c[1]));
full_Adder M2(.D1(a[2]), .D2(b[2]), .Cin(c[1]), .Sum_out(sum[2]), .Cout(c[2]));
full_Adder M3(.D1(a[3]), .D2(b[3]), .Cin(c[2]), .Sum_out(sum[3]), .Cout(cout));

    
endmodule

verilog/task1/subtask4/tb.v
`timescale 1ns/1ns

module tb; 
  reg [3:0]a,b;
  reg cin;
  wire [3:0]sum;
  wire cout;

  rca4 M0(.a(a), .b(b), .cin(cin), .sum(sum), .cout(cout));

  task delay;
    begin
      #10;
    end
    endtask

    task stimulus (input [3:0]a1,b1,input c1);
    begin
        a = a1;
        b = b1;
        cin = c1;
    end
    endtask

  integer i,j,k;
  initial begin
    $dumpfile("dump.vcd");
    $dumpvars(0,tb);

    for(i=0;i<2;i=i+1) begin
      for(j=0;j<16;j=j+1) begin
        for(k=0;k<16;k=k+1) begin
            stimulus(j,k,i);
            delay;
      end
    end
  end
  $finish;
  end

  initial $monitor($time," ns A = %b, B = %b, Cin = %b, Cout = %b, Sum = %b",a,b,cin,cout,sum);

endmodule

verilog/task1/subtask4/dump.vcd
$date
	Thu Jul 13 12:23:07 2023
$end
$version
	Icarus Verilog
$end
$timescale
	1ns
$end
$scope module tb $end
$var wire 4 ! sum [3:0] $end
$var wire 1 " cout $end
$var reg 4 # a [3:0] $end
$var reg 4 $ b [3:0] $end
$var reg 1 % cin $end
$var integer 32 & i [31:0] $end
$var integer 32 ' j [31:0] $end
$var integer 32 ( k [31:0] $end
$scope module M0 $end
$var wire 4 ) a [3:0] $end
$var wire 4 * b [3:0] $end
$var wire 1 % cin $end
$var wire 4 + sum [3:0] $end
$var wire 1 " cout $end
$var wire 3 , c [2:0] $end
$scope module M0 $end
$var wire 1 % Cin $end
$var wire 1 - Cout $end
$var wire 1 . D1 $end
$var wire 1 / D2 $end
$var wire 1 0 Sum_out $end
$var wire 1 1 a1 $end
$var wire 1 2 a2 $end
$var wire 1 3 a3 $end
$upscope $end
$scope module M1 $end
$var wire 1 4 Cin $end
$var wire 1 5 Cout $end
$var wire 1 6 D1 $end
$var wire 1 7 D2 $end
$var wire 1 8 Sum_out $end
$var wire 1 9 a1 $end
$var wire 1 : a2 $end
$var wire 1 ; a3 $end
$upscope $end
$scope module M2 $end
$var wire 1 < Cin $end
$var wire 1 = Cout $end
$var wire 1 > D1 $end
$var wire 1 ? D2 $end
$var wire 1 @ Sum_out $end
$var wire 1 A a1 $end
$var wire 1 B a2 $end
$var wire 1 C a3 $end
$upscope $end
$scope module M3 $end
$var wire 1 D Cin $end
$var wire 1 " Cout $end
$var wire 1 E D1 $end
$var wire 1 F D2 $end
$var wire 1 G Sum_out $end
$var wire 1 H a1 $end
$var wire 1 I a2 $end
$var wire 1 J a3 $end
$upscope $end
$upscope $end
$scope task delay $end
$upscope $end
$scope task stimulus $end
$var reg 4 K a1 [3:0] $end
$var reg 4 L b1 [3:0] $end
$var reg 1 M c1 $end
$upscope $end
$upscope $end
$enddefinitions $end
#0
$dumpvars
0M
b0 L
b0 K
0J
0I
0H
0G
0F
0E
0D
0C
0B
0A
0@
0?
0>
0=
0<
0;
0:
09
08
07
06
05
04
03
02
01
00
0/
0.
0-
b0 ,
b0 +
b0 *
b0 )
b0 (
b0 '
b0 &
0%
b0 $
b0 #
0"
b0 !
$end
#10
b1 !
b1 +
10
11
1/
b1 $
b1 *
b1 L
b1 (
#20
00
b10 !
b10 +
18
01
19
0/
17
b10 $
b10 *
b10 L
b10 (
#30
b11 !
b11 +
10
11
1/
b11 $
b11 *
b11 L
b11 (
#40
00
08
b100 !
b100 +
1@
01
09
1A
0/
07
1?
b100 $
b100 *
b100 L
b100 (
#50
b101 !
b101 +
10
11
1/
b101 $
b101 *
b101 L
b101 (
#60
00
b110 !
b110 +
18
01
19
0/
17
b110 $
b110 *
b110 L
b110 (
#70
b111 !
b111 +
10
11
1/
b111 $
b111 *
b111 L
b111 (
#80
00
08
0@
b1000 !
b1000 +
1G
01
09
0A
1H
0/
07
0?
1F
b1000 $
b1000 *
b1000 L
b1000 (
#90
b1001 !
b1001 +
10
11
1/
b1001 $
b1001 *
b1001 L
b1001 (
#100
00
b1010 !
b1010 +
18
01
19
0/
17
b1010 $
b1010 *
b1010 L
b1010 (
#110
b1011 !
b1011 +
10
11
1/
b1011 $
b1011 *
b1011 L
b1011 (
#120
00
08
b1100 !
b1100 +
1@
01
09
1A
0/
07
1?
b1100 $
b1100 *
b1100 L
b1100 (
#130
b1101 !
b1101 +
10
11
1/
b1101 $
b1101 *
b1101 L
b1101 (
#140
00
b1110 !
b1110 +
18
01
19
0/
17
b1110 $
b1110 *
b1110 L
b1110 (
#150
b1111 !
b1111 +
10
11
1/
b1111 $
b1111 *
b1111 L
b1111 (
#160
08
0@
b1 !
b1 +
0G
09
0A
0H
0/
07
0?
0F
1.
b0 $
b0 *
b1 #
b1 )
b0 L
b1 K
b1 '
b0 (
#170
18
14
b10 !
b10 +
00
b1 ,
1-
01
12
1/
b1 $
b1 *
b1 L
b1 (
#180
0@
0<
04
05
10
b0 ,
0-
0;
b11 !
b11 +
18
11
02
19
0/
17
b10 $
b10 *
b10 L
b10 (
#190
1@
1<
15
1;
08
14
b100 !
b100 +
00
b11 ,
1-
01
12
1/
b11 $
b11 *
b11 L
b11 (
#200
0G
0<
0D
04
05
0=
10
b0 ,
0-
0;
08
0C
b101 !
b101 +
1@
11
02
09
1A
0/
07
1?
b100 $
b100 *
b100 L
b100 (
#210
18
14
b110 !
b110 +
00
b1 ,
1-
01
12
1/
b101 $
b101 *
b101 L
b101 (
#220
0G
0D
0=
0C
1@
0<
04
05
10
b0 ,
0-
0;
b111 !
b111 +
18
11
02
19
0/
17
b110 $
b110 *
b110 L
b110 (
#230
1G
1D
1=
1C
0@
1<
15
1;
08
14
b1000 !
b1000 +
00
b111 ,
1-
01
12
1/
b111 $
b111 *
b111 L
b111 (
#240
0<
0D
04
05
0=
0"
10
b0 ,
0-
0;
08
0C
0@
0J
b1001 !
b1001 +
1G
11
02
09
0A
1H
0/
07
0?
1F
b1000 $
b1000 *
b1000 L
b1000 (
#250
18
14
b1010 !
b1010 +
00
b1 ,
1-
01
12
1/
b1001 $
b1001 *
b1001 L
b1001 (
#260
0@
0<
04
05
10
b0 ,
0-
0;
b1011 !
b1011 +
18
11
02
19
0/
17
b1010 $
b1010 *
b1010 L
b1010 (
#270
1@
1<
15
1;
08
14
b1100 !
b1100 +
00
b11 ,
1-
01
12
1/
b1011 $
b1011 *
b1011 L
b1011 (
#280
0"
0J
1G
0<
0D
04
05
0=
10
b0 ,
0-
0;
08
0C
b1101 !
b1101 +
1@
11
02
09
1A
0/
07
1?
b1100 $
b1100 *
b1100 L
b1100 (
#290
18
14
b1110 !
b1110 +
00
b1 ,
1-
01
12
1/
b1101 $
b1101 *
b1101 L
b1101 (
#300
0"
0J
1G
0D
0=
0C
1@
0<
04
05
10
b0 ,
0-
0;
b1111 !
b1111 +
18
11
02
19
0/
17
b1110 $
b1110 *
b1110 L
b1110 (
#310
1"
1J
0G
1D
1=
1C
0@
1<
15
1;
08
14
b0 !
b0 +
00
b111 ,
1-
01
12
1/
b1111 $
b1111 *
b1111 L
b1111 (
#320
0<
05
0D
0;
18
0=
0"
04
0C
0@
0J
b10 !
b10 +
0G
b0 ,
0-
0A
0H
02
0/
07
0?
0F
0.
16
b0 $
b0 *
b10 #
b10 )
b0 L
b10 K
b10 '
b0 (
#330
b11 !
b11 +
10
11
1/
b1 $
b1 *
b1 L
b1 (
#340
1@
1<
00
b100 !
b100 +
08
b10 ,
15
01
09
1:
0/
17
b10 $
b10 *
b10 L
b10 (
#350
b101 !
b101 +
10
11
1/
b11 $
b11 *
b11 L
b11 (
#360
0G
0D
0<
0=
00
18
b0 ,
05
0C
b110 !
b110 +
1@
01
19
0:
1A
0/
07
1?
b100 $
b100 *
b100 L
b100 (
#370
b111 !
b111 +
10
11
1/
b101 $
b101 *
b101 L
b101 (
#380
1G
1D
1=
1C
0@
1<
00
b1000 !
b1000 +
08
b110 ,
15
01
09
1:
0/
17
b110 $
b110 *
b110 L
b110 (
#390
b1001 !
b1001 +
10
11
1/
b111 $
b111 *
b111 L
b111 (
#400
0D
0<
0=
0"
00
18
b0 ,
05
0C
0@
0J
b1010 !
b1010 +
1G
01
19
0:
0A
1H
0/
07
0?
1F
b1000 $
b1000 *
b1000 L
b1000 (
#410
b1011 !
b1011 +
10
11
1/
b1001 $
b1001 *
b1001 L
b1001 (
#420
1@
1<
00
b1100 !
b1100 +
08
b10 ,
15
01
09
1:
0/
17
b1010 $
b1010 *
b1010 L
b1010 (
#430
b1101 !
b1101 +
10
11
1/
b1011 $
b1011 *
b1011 L
b1011 (
#440
0"
0J
1G
0D
0<
0=
00
18
b0 ,
05
0C
b1110 !
b1110 +
1@
01
19
0:
1A
0/
07
1?
b1100 $
b1100 *
b1100 L
b1100 (
#450
b1111 !
b1111 +
10
11
1/
b1101 $
b1101 *
b1101 L
b1101 (
#460
1"
1J
0G
1D
1=
1C
0@
1<
00
b0 !
b0 +
08
b110 ,
15
01
09
1:
0/
17
b1110 $
b1110 *
b1110 L
b1110 (
#470
b1 !
b1 +
10
11
1/
b1111 $
b1111 *
b1111 L
b1111 (
#480
0D
0<
0=
0"
18
b0 ,
05
0C
0@
0J
b11 !
b11 +
0G
19
0:
0A
0H
0/
07
0?
0F
1.
b0 $
b0 *
b11 #
b11 )
b0 L
b11 K
b11 '
b0 (
#490
1@
1<
15
1;
08
14
b100 !
b100 +
00
b11 ,
1-
01
12
1/
b1 $
b1 *
b1 L
b1 (
#500
04
10
b10 ,
0-
0;
b101 !
b101 +
08
11
02
09
1:
0/
17
b10 $
b10 *
b10 L
b10 (
#510
18
14
b110 !
b110 +
00
b11 ,
1-
01
12
1/
b11 $
b11 *
b11 L
b11 (
#520
0G
0D
04
0<
0=
10
0-
0;
18
b0 ,
05
0C
b111 !
b111 +
1@
11
02
19
0:
1A
0/
07
1?
b100 $
b100 *
b100 L
b100 (
#530
1G
1D
1=
1C
0@
1<
15
1;
08
14
b1000 !
b1000 +
00
b111 ,
1-
01
12
1/
b101 $
b101 *
b101 L
b101 (
#540
04
10
b110 ,
0-
0;
b1001 !
b1001 +
08
11
02
09
1:
0/
17
b110 $
b110 *
b110 L
b110 (
#550
18
14
b1010 !
b1010 +
00
b111 ,
1-
01
12
1/
b111 $
b111 *
b111 L
b111 (
#560
0D
04
0<
0=
0"
10
0-
0;
18
b0 ,
05
0C
0@
0J
b1011 !
b1011 +
1G
11
02
19
0:
0A
1H
0/
07
0?
1F
b1000 $
b1000 *
b1000 L
b1000 (
#570
1@
1<
15
1;
08
14
b1100 !
b1100 +
00
b11 ,
1-
01
12
1/
b1001 $
b1001 *
b1001 L
b1001 (
#580
04
10
b10 ,
0-
0;
b1101 !
b1101 +
08
11
02
09
1:
0/
17
b1010 $
b1010 *
b1010 L
b1010 (
#590
18
14
b1110 !
b1110 +
00
b11 ,
1-
01
12
1/
b1011 $
b1011 *
b1011 L
b1011 (
#600
0"
0J
1G
0D
04
0<
0=
10
0-
0;
18
b0 ,
05
0C
b1111 !
b1111 +
1@
11
02
19
0:
1A
0/
07
1?
b1100 $
b1100 *
b1100 L
b1100 (
#610
1"
1J
0G
1D
1=
1C
0@
1<
15
1;
08
14
b0 !
b0 +
00
b111 ,
1-
01
12
1/
b1101 $
b1101 *
b1101 L
b1101 (
#620
04
10
b110 ,
0-
0;
b1 !
b1 +
08
11
02
09
1:
0/
17
b1110 $
b1110 *
b1110 L
b1110 (
#630
18
14
b10 !
b10 +
00
b111 ,
1-
01
12
1/
b1111 $
b1111 *
b1111 L
b1111 (
#640
0D
0=
08
0C
1@
0"
04
0<
0J
b100 !
b100 +
0G
0-
b0 ,
05
0H
02
0:
0/
07
0?
0F
0.
06
1>
b0 $
b0 *
b100 #
b100 )
b0 L
b100 K
b100 '
b0 (
#650
b101 !
b101 +
10
11
1/
b1 $
b1 *
b1 L
b1 (
#660
00
b110 !
b110 +
18
01
19
0/
17
b10 $
b10 *
b10 L
b10 (
#670
b111 !
b111 +
10
11
1/
b11 $
b11 *
b11 L
b11 (
#680
1G
1D
00
08
b1000 !
b1000 +
0@
b100 ,
1=
01
09
0A
1B
0/
07
1?
b100 $
b100 *
b100 L
b100 (
#690
b1001 !
b1001 +
10
11
1/
b101 $
b101 *
b101 L
b101 (
#700
00
b1010 !
b1010 +
18
01
19
0/
17
b110 $
b110 *
b110 L
b110 (
#710
b1011 !
b1011 +
10
11
1/
b111 $
b111 *
b111 L
b111 (
#720
0D
0"
00
08
1@
b0 ,
0=
0J
b1100 !
b1100 +
1G
01
09
1A
0B
1H
0/
07
0?
1F
b1000 $
b1000 *
b1000 L
b1000 (
#730
b1101 !
b1101 +
10
11
1/
b1001 $
b1001 *
b1001 L
b1001 (
#740
00
b1110 !
b1110 +
18
01
19
0/
17
b1010 $
b1010 *
b1010 L
b1010 (
#750
b1111 !
b1111 +
10
11
1/
b1011 $
b1011 *
b1011 L
b1011 (
#760
1"
1J
0G
1D
00
08
b0 !
b0 +
0@
b100 ,
1=
01
09
0A
1B
0/
07
1?
b1100 $
b1100 *
b1100 L
b1100 (
#770
b1 !
b1 +
10
11
1/
b1101 $
b1101 *
b1101 L
b1101 (
#780
00
b10 !
b10 +
18
01
19
0/
17
b1110 $
b1110 *
b1110 L
b1110 (
#790
b11 !
b11 +
10
11
1/
b1111 $
b1111 *
b1111 L
b1111 (
#800
0D
0"
08
1@
b0 ,
0=
0J
b101 !
b101 +
0G
09
1A
0B
0H
0/
07
0?
0F
1.
b0 $
b0 *
b101 #
b101 )
b0 L
b101 K
b101 '
b0 (
#810
18
14
b110 !
b110 +
00
b1 ,
1-
01
12
1/
b1 $
b1 *
b1 L
b1 (
#820
0G
0D
0=
0C
1@
0<
04
05
10
b0 ,
0-
0;
b111 !
b111 +
18
11
02
19
0/
17
b10 $
b10 *
b10 L
b10 (
#830
1G
1D
1=
1C
0@
1<
15
1;
08
14
b1000 !
b1000 +
00
b111 ,
1-
01
12
1/
b11 $
b11 *
b11 L
b11 (
#840
0<
04
05
10
b100 ,
0-
0;
08
0C
b1001 !
b1001 +
0@
11
02
09
0A
1B
0/
07
1?
b100 $
b100 *
b100 L
b100 (
#850
18
14
b1010 !
b1010 +
00
b101 ,
1-
01
12
1/
b101 $
b101 *
b101 L
b101 (
#860
0@
0<
04
05
10
b100 ,
0-
0;
b1011 !
b1011 +
18
11
02
19
0/
17
b110 $
b110 *
b110 L
b110 (
#870
1@
1<
15
1;
08
14
b1100 !
b1100 +
00
b111 ,
1-
01
12
1/
b111 $
b111 *
b111 L
b111 (
#880
0<
04
05
0D
0"
10
0-
0;
08
0C
1@
b0 ,
0=
0J
b1101 !
b1101 +
1G
11
02
09
1A
0B
1H
0/
07
0?
1F
b1000 $
b1000 *
b1000 L
b1000 (
#890
18
14
b1110 !
b1110 +
00
b1 ,
1-
01
12
1/
b1001 $
b1001 *
b1001 L
b1001 (
#900
0"
0J
1G
0D
0=
0C
1@
0<
04
05
10
b0 ,
0-
0;
b1111 !
b1111 +
18
11
02
19
0/
17
b1010 $
b1010 *
b1010 L
b1010 (
#910
1"
1J
0G
1D
1=
1C
0@
1<
15
1;
08
14
b0 !
b0 +
00
b111 ,
1-
01
12
1/
b1011 $
b1011 *
b1011 L
b1011 (
#920
0<
04
05
10
b100 ,
0-
0;
08
0C
b1 !
b1 +
0@
11
02
09
0A
1B
0/
07
1?
b1100 $
b1100 *
b1100 L
b1100 (
#930
18
14
b10 !
b10 +
00
b101 ,
1-
01
12
1/
b1101 $
b1101 *
b1101 L
b1101 (
#940
0@
0<
04
05
10
b100 ,
0-
0;
b11 !
b11 +
18
11
02
19
0/
17
b1110 $
b1110 *
b1110 L
b1110 (
#950
1@
1<
15
1;
08
14
b100 !
b100 +
00
b111 ,
1-
01
12
1/
b1111 $
b1111 *
b1111 L
b1111 (
#960
0<
05
0;
18
0D
0"
04
0C
1@
0=
0J
b110 !
b110 +
0G
b0 ,
0-
1A
0B
0H
02
0/
07
0?
0F
0.
16
b0 $
b0 *
b110 #
b110 )
b0 L
b110 K
b110 '
b0 (
#970
b111 !
b111 +
10
11
1/
b1 $
b1 *
b1 L
b1 (
#980
1G
1D
1=
1C
0@
1<
00
b1000 !
b1000 +
08
b110 ,
15
01
09
1:
0/
17
b10 $
b10 *
b10 L
b10 (
#990
b1001 !
b1001 +
10
11
1/
b11 $
b11 *
b11 L
b11 (
#1000
0<
00
18
b100 ,
05
0C
b1010 !
b1010 +
0@
01
19
0:
0A
1B
0/
07
1?
b100 $
b100 *
b100 L
b100 (
#1010
b1011 !
b1011 +
10
11
1/
b101 $
b101 *
b101 L
b101 (
#1020
1@
1<
00
b1100 !
b1100 +
08
b110 ,
15
01
09
1:
0/
17
b110 $
b110 *
b110 L
b110 (
#1030
b1101 !
b1101 +
10
11
1/
b111 $
b111 *
b111 L
b111 (
#1040
0<
0D
0"
00
18
05
0C
1@
b0 ,
0=
0J
b1110 !
b1110 +
1G
01
19
0:
1A
0B
1H
0/
07
0?
1F
b1000 $
b1000 *
b1000 L
b1000 (
#1050
b1111 !
b1111 +
10
11
1/
b1001 $
b1001 *
b1001 L
b1001 (
#1060
1"
1J
0G
1D
1=
1C
0@
1<
00
b0 !
b0 +
08
b110 ,
15
01
09
1:
0/
17
b1010 $
b1010 *
b1010 L
b1010 (
#1070
b1 !
b1 +
10
11
1/
b1011 $
b1011 *
b1011 L
b1011 (
#1080
0<
00
18
b100 ,
05
0C
b10 !
b10 +
0@
01
19
0:
0A
1B
0/
07
1?
b1100 $
b1100 *
b1100 L
b1100 (
#1090
b11 !
b11 +
10
11
1/
b1101 $
b1101 *
b1101 L
b1101 (
#1100
1@
1<
00
b100 !
b100 +
08
b110 ,
15
01
09
1:
0/
17
b1110 $
b1110 *
b1110 L
b1110 (
#1110
b101 !
b101 +
10
11
1/
b1111 $
b1111 *
b1111 L
b1111 (
#1120
0<
0D
0"
18
05
0C
1@
b0 ,
0=
0J
b111 !
b111 +
0G
19
0:
1A
0B
0H
0/
07
0?
0F
1.
b0 $
b0 *
b111 #
b111 )
b0 L
b111 K
b111 '
b0 (
#1130
1G
1D
1=
1C
0@
1<
15
1;
08
14
b1000 !
b1000 +
00
b111 ,
1-
01
12
1/
b1 $
b1 *
b1 L
b1 (
#1140
04
10
b110 ,
0-
0;
b1001 !
b1001 +
08
11
02
09
1:
0/
17
b10 $
b10 *
b10 L
b10 (
#1150
18
14
b1010 !
b1010 +
00
b111 ,
1-
01
12
1/
b11 $
b11 *
b11 L
b11 (
#1160
04
0<
10
0-
0;
18
b100 ,
05
0C
b1011 !
b1011 +
0@
11
02
19
0:
0A
1B
0/
07
1?
b100 $
b100 *
b100 L
b100 (
#1170
1@
1<
15
1;
08
14
b1100 !
b1100 +
00
b111 ,
1-
01
12
1/
b101 $
b101 *
b101 L
b101 (
#1180
04
10
b110 ,
0-
0;
b1101 !
b1101 +
08
11
02
09
1:
0/
17
b110 $
b110 *
b110 L
b110 (
#1190
18
14
b1110 !
b1110 +
00
b111 ,
1-
01
12
1/
b111 $
b111 *
b111 L
b111 (
#1200
04
0<
0D
0"
10
0-
0;
18
05
0C
1@
b0 ,
0=
0J
b1111 !
b1111 +
1G
11
02
19
0:
1A
0B
1H
0/
07
0?
1F
b1000 $
b1000 *
b1000 L
b1000 (
#1210
1"
1J
0G
1D
1=
1C
0@
1<
15
1;
08
14
b0 !
b0 +
00
b111 ,
1-
01
12
1/
b1001 $
b1001 *
b1001 L
b1001 (
#1220
04
10
b110 ,
0-
0;
b1 !
b1 +
08
11
02
09
1:
0/
17
b1010 $
b1010 *
b1010 L
b1010 (
#1230
18
14
b10 !
b10 +
00
b111 ,
1-
01
12
1/
b1011 $
b1011 *
b1011 L
b1011 (
#1240
04
0<
10
0-
0;
18
b100 ,
05
0C
b11 !
b11 +
0@
11
02
19
0:
0A
1B
0/
07
1?
b1100 $
b1100 *
b1100 L
b1100 (
#1250
1@
1<
15
1;
08
14
b100 !
b100 +
00
b111 ,
1-
01
12
1/
b1101 $
b1101 *
b1101 L
b1101 (
#1260
04
10
b110 ,
0-
0;
b101 !
b101 +
08
11
02
09
1:
0/
17
b1110 $
b1110 *
b1110 L
b1110 (
#1270
18
14
b110 !
b110 +
00
b111 ,
1-
01
12
1/
b1111 $
b1111 *
b1111 L
b1111 (
#1280
0"
08
0@
0J
b1000 !
b1000 +
1G
04
0<
0D
0-
05
b0 ,
0=
02
0:
0B
0/
07
0?
0F
0.
06
0>
1E
b0 $
b0 *
b1000 #
b1000 )
b0 L
b1000 K
b1000 '
b0 (
#1290
b1001 !
b1001 +
10
11
1/
b1 $
b1 *
b1 L
b1 (
#1300
00
b1010 !
b1010 +
18
01
19
0/
17
b10 $
b10 *
b10 L
b10 (
#1310
b1011 !
b1011 +
10
11
1/
b11 $
b11 *
b11 L
b11 (
#1320
00
08
b1100 !
b1100 +
1@
01
09
1A
0/
07
1?
b100 $
b100 *
b100 L
b100 (
#1330
b1101 !
b1101 +
10
11
1/
b101 $
b101 *
b101 L
b101 (
#1340
00
b1110 !
b1110 +
18
01
19
0/
17
b110 $
b110 *
b110 L
b110 (
#1350
b1111 !
b1111 +
10
11
1/
b111 $
b111 *
b111 L
b111 (
#1360
00
08
0@
b0 !
b0 +
0G
1"
01
09
0A
0H
1I
0/
07
0?
1F
b1000 $
b1000 *
b1000 L
b1000 (
#1370
b1 !
b1 +
10
11
1/
b1001 $
b1001 *
b1001 L
b1001 (
#1380
00
b10 !
b10 +
18
01
19
0/
17
b1010 $
b1010 *
b1010 L
b1010 (
#1390
b11 !
b11 +
10
11
1/
b1011 $
b1011 *
b1011 L
b1011 (
#1400
00
08
b100 !
b100 +
1@
01
09
1A
0/
07
1?
b1100 $
b1100 *
b1100 L
b1100 (
#1410
b101 !
b101 +
10
11
1/
b1101 $
b1101 *
b1101 L
b1101 (
#1420
00
b110 !
b110 +
18
01
19
0/
17
b1110 $
b1110 *
b1110 L
b1110 (
#1430
b111 !
b111 +
10
11
1/
b1111 $
b1111 *
b1111 L
b1111 (
#1440
08
0@
b1001 !
b1001 +
1G
0"
09
0A
1H
0I
0/
07
0?
0F
1.
b0 $
b0 *
b1001 #
b1001 )
b0 L
b1001 K
b1001 '
b0 (
#1450
18
14
b1010 !
b1010 +
00
b1 ,
1-
01
12
1/
b1 $
b1 *
b1 L
b1 (
#1460
0@
0<
04
05
10
b0 ,
0-
0;
b1011 !
b1011 +
18
11
02
19
0/
17
b10 $
b10 *
b10 L
b10 (
#1470
1@
1<
15
1;
08
14
b1100 !
b1100 +
00
b11 ,
1-
01
12
1/
b11 $
b11 *
b11 L
b11 (
#1480
0"
0J
1G
0<
0D
04
05
0=
10
b0 ,
0-
0;
08
0C
b1101 !
b1101 +
1@
11
02
09
1A
0/
07
1?
b100 $
b100 *
b100 L
b100 (
#1490
18
14
b1110 !
b1110 +
00
b1 ,
1-
01
12
1/
b101 $
b101 *
b101 L
b101 (
#1500
0"
0J
1G
0D
0=
0C
1@
0<
04
05
10
b0 ,
0-
0;
b1111 !
b1111 +
18
11
02
19
0/
17
b110 $
b110 *
b110 L
b110 (
#1510
1"
1J
0G
1D
1=
1C
0@
1<
15
1;
08
14
b0 !
b0 +
00
b111 ,
1-
01
12
1/
b111 $
b111 *
b111 L
b111 (
#1520
0<
0D
04
05
0=
10
b0 ,
0-
0;
08
0C
0@
0J
b1 !
b1 +
0G
11
02
09
0A
0H
1I
0/
07
0?
1F
b1000 $
b1000 *
b1000 L
b1000 (
#1530
18
14
b10 !
b10 +
00
b1 ,
1-
01
12
1/
b1001 $
b1001 *
b1001 L
b1001 (
#1540
0@
0<
04
05
10
b0 ,
0-
0;
b11 !
b11 +
18
11
02
19
0/
17
b1010 $
b1010 *
b1010 L
b1010 (
#1550
1@
1<
15
1;
08
14
b100 !
b100 +
00
b11 ,
1-
01
12
1/
b1011 $
b1011 *
b1011 L
b1011 (
#1560
0G
0<
0D
04
05
0=
10
b0 ,
0-
0;
08
0C
b101 !
b101 +
1@
11
02
09
1A
0/
07
1?
b1100 $
b1100 *
b1100 L
b1100 (
#1570
18
14
b110 !
b110 +
00
b1 ,
1-
01
12
1/
b1101 $
b1101 *
b1101 L
b1101 (
#1580
0G
0D
0=
0C
1@
0<
04
05
10
b0 ,
0-
0;
b111 !
b111 +
18
11
02
19
0/
17
b1110 $
b1110 *
b1110 L
b1110 (
#1590
1G
1D
1=
1C
0@
1<
15
1;
08
14
b1000 !
b1000 +
00
b111 ,
1-
01
12
1/
b1111 $
b1111 *
b1111 L
b1111 (
#1600
0<
05
0D
0;
18
0=
04
0C
0@
0J
b1010 !
b1010 +
1G
0"
b0 ,
0-
0A
1H
0I
02
0/
07
0?
0F
0.
16
b0 $
b0 *
b1010 #
b1010 )
b0 L
b1010 K
b1010 '
b0 (
#1610
b1011 !
b1011 +
10
11
1/
b1 $
b1 *
b1 L
b1 (
#1620
1@
1<
00
b1100 !
b1100 +
08
b10 ,
15
01
09
1:
0/
17
b10 $
b10 *
b10 L
b10 (
#1630
b1101 !
b1101 +
10
11
1/
b11 $
b11 *
b11 L
b11 (
#1640
0"
0J
1G
0D
0<
0=
00
18
b0 ,
05
0C
b1110 !
b1110 +
1@
01
19
0:
1A
0/
07
1?
b100 $
b100 *
b100 L
b100 (
#1650
b1111 !
b1111 +
10
11
1/
b101 $
b101 *
b101 L
b101 (
#1660
1"
1J
0G
1D
1=
1C
0@
1<
00
b0 !
b0 +
08
b110 ,
15
01
09
1:
0/
17
b110 $
b110 *
b110 L
b110 (
#1670
b1 !
b1 +
10
11
1/
b111 $
b111 *
b111 L
b111 (
#1680
0D
0<
0=
00
18
b0 ,
05
0C
0@
0J
b10 !
b10 +
0G
01
19
0:
0A
0H
1I
0/
07
0?
1F
b1000 $
b1000 *
b1000 L
b1000 (
#1690
b11 !
b11 +
10
11
1/
b1001 $
b1001 *
b1001 L
b1001 (
#1700
1@
1<
00
b100 !
b100 +
08
b10 ,
15
01
09
1:
0/
17
b1010 $
b1010 *
b1010 L
b1010 (
#1710
b101 !
b101 +
10
11
1/
b1011 $
b1011 *
b1011 L
b1011 (
#1720
0G
0D
0<
0=
00
18
b0 ,
05
0C
b110 !
b110 +
1@
01
19
0:
1A
0/
07
1?
b1100 $
b1100 *
b1100 L
b1100 (
#1730
b111 !
b111 +
10
11
1/
b1101 $
b1101 *
b1101 L
b1101 (
#1740
1G
1D
1=
1C
0@
1<
00
b1000 !
b1000 +
08
b110 ,
15
01
09
1:
0/
17
b1110 $
b1110 *
b1110 L
b1110 (
#1750
b1001 !
b1001 +
10
11
1/
b1111 $
b1111 *
b1111 L
b1111 (
#1760
0D
0<
0=
18
b0 ,
05
0C
0@
0J
b1011 !
b1011 +
1G
0"
19
0:
0A
1H
0I
0/
07
0?
0F
1.
b0 $
b0 *
b1011 #
b1011 )
b0 L
b1011 K
b1011 '
b0 (
#1770
1@
1<
15
1;
08
14
b1100 !
b1100 +
00
b11 ,
1-
01
12
1/
b1 $
b1 *
b1 L
b1 (
#1780
04
10
b10 ,
0-
0;
b1101 !
b1101 +
08
11
02
09
1:
0/
17
b10 $
b10 *
b10 L
b10 (
#1790
18
14
b1110 !
b1110 +
00
b11 ,
1-
01
12
1/
b11 $
b11 *
b11 L
b11 (
#1800
0"
0J
1G
0D
04
0<
0=
10
0-
0;
18
b0 ,
05
0C
b1111 !
b1111 +
1@
11
02
19
0:
1A
0/
07
1?
b100 $
b100 *
b100 L
b100 (
#1810
1"
1J
0G
1D
1=
1C
0@
1<
15
1;
08
14
b0 !
b0 +
00
b111 ,
1-
01
12
1/
b101 $
b101 *
b101 L
b101 (
#1820
04
10
b110 ,
0-
0;
b1 !
b1 +
08
11
02
09
1:
0/
17
b110 $
b110 *
b110 L
b110 (
#1830
18
14
b10 !
b10 +
00
b111 ,
1-
01
12
1/
b111 $
b111 *
b111 L
b111 (
#1840
0D
04
0<
0=
10
0-
0;
18
b0 ,
05
0C
0@
0J
b11 !
b11 +
0G
11
02
19
0:
0A
0H
1I
0/
07
0?
1F
b1000 $
b1000 *
b1000 L
b1000 (
#1850
1@
1<
15
1;
08
14
b100 !
b100 +
00
b11 ,
1-
01
12
1/
b1001 $
b1001 *
b1001 L
b1001 (
#1860
04
10
b10 ,
0-
0;
b101 !
b101 +
08
11
02
09
1:
0/
17
b1010 $
b1010 *
b1010 L
b1010 (
#1870
18
14
b110 !
b110 +
00
b11 ,
1-
01
12
1/
b1011 $
b1011 *
b1011 L
b1011 (
#1880
0G
0D
04
0<
0=
10
0-
0;
18
b0 ,
05
0C
b111 !
b111 +
1@
11
02
19
0:
1A
0/
07
1?
b1100 $
b1100 *
b1100 L
b1100 (
#1890
1G
1D
1=
1C
0@
1<
15
1;
08
14
b1000 !
b1000 +
00
b111 ,
1-
01
12
1/
b1101 $
b1101 *
b1101 L
b1101 (
