verilog/task1/subtask2/mux2x1.v
//`timescale 10ns/1ps
module mux2x1(
    input [1:0]I,
    input S,
    output Y
);
    assign Y = S ? I[1]: I[0];
    
endmodule

verilog/task1/subtask2/mux4x1.v
//`timescale 10ns/1ps
`include "mux2x1.v"
module mux4x1(
    input [3:0] I,
    input [1:0] S,
    output Y
);

wire [1:0]w;

mux2x1 M1(.I(I[1:0]), .S(S[0]), .Y(w[0]));
mux2x1 M2(.I(I[3:2]), .S(S[0]), .Y(w[1]));
mux2x1 M3(.I(w), .S(S[1]), .Y(Y));
    
endmodule

verilog/task1/subtask2/mux4x1_tb.v

`timescale 1ns/1ps
module mux4x1_tb;
    reg [3:0]I;
    reg [1:0]S;
    wire Y;

    mux4x1 M1(.I(I), .S(S), .Y(Y));

    task delay;
    begin
      #10;
    end
    endtask

    task stimulus (input [3:0]a, input [1:0]select);
    begin
        I = a;
        S = select;
    end
    endtask

    task initialize;
    begin
      I = 4'b0000;
      S = 2'b00;
    end
    endtask

    integer i,j;
    initial begin
        $dumpfile("mux4x1.vcd");
        $dumpvars(0,mux4x1_tb);

        initialize;
        delay;

        for(i=0 ; i<16; i=i+1) begin
          for(j=0; j<4; j=j+1) begin
            stimulus(i,j);
            delay;
          end
        end

        $finish;
    end

    initial $monitor($time,"ns S = %b, I = %b, Y = %b",S, I, Y);


endmodule

verilog/task1/subtask2/mux4x1.vcd
$date
	Thu Jul 13 11:55:45 2023
$end
$version
	Icarus Verilog
$end
$timescale
	1ps
$end
$scope module mux4x1_tb $end
$var wire 1 ! Y $end
$var reg 4 " I [3:0] $end
$var reg 2 # S [1:0] $end
$var integer 32 $ i [31:0] $end
$var integer 32 % j [31:0] $end
$scope module M1 $end
$var wire 4 & I [3:0] $end
$var wire 2 ' S [1:0] $end
$var wire 2 ( w [1:0] $end
$var wire 1 ! Y $end
$scope module M1 $end
$var wire 2 ) I [1:0] $end
$var wire 1 * S $end
$var wire 1 + Y $end
$upscope $end
$scope module M2 $end
$var wire 2 , I [1:0] $end
$var wire 1 - S $end
$var wire 1 . Y $end
$upscope $end
$scope module M3 $end
$var wire 2 / I [1:0] $end
$var wire 1 0 S $end
$var wire 1 ! Y $end
$upscope $end
$upscope $end
$scope task delay $end
$upscope $end
$scope task initialize $end
$upscope $end
$scope task stimulus $end
$var reg 4 1 a [3:0] $end
$var reg 2 2 select [1:0] $end
$upscope $end
$upscope $end
$enddefinitions $end
#0
$dumpvars
bx 2
bx 1
00
b0 /
0.
0-
b0 ,
0+
0*
b0 )
b0 (
b0 '
b0 &
bx %
bx $
b0 #
b0 "
0!
$end
#10000
b0 2
b0 1
b0 %
b0 $
#20000
1*
1-
b1 #
b1 '
b1 2
b1 %
#30000
0*
0-
10
b10 #
b10 '
b10 2
b10 %
#40000
1*
1-
b11 #
b11 '
b11 2
b11 %
#50000
1!
b1 (
b1 /
1+
0*
0-
00
b1 )
b0 #
b0 '
b1 "
b1 &
b0 2
b1 1
b1 $
b0 %
#60000
0!
b0 (
b0 /
0+
1*
1-
b1 #
b1 '
b1 2
b1 %
#70000
b1 (
b1 /
1+
0*
0-
10
b10 #
b10 '
b10 2
b10 %
#80000
b0 (
b0 /
0+
1*
1-
b11 #
b11 '
b11 2
b11 %
#90000
0*
0-
00
b10 )
b0 #
b0 '
b10 "
b10 &
b0 2
b10 1
b10 $
b0 %
#100000
1!
b1 (
b1 /
1+
1*
1-
b1 #
b1 '
b1 2
b1 %
#110000
b0 (
b0 /
0+
0!
0*
0-
10
b10 #
b10 '
b10 2
b10 %
#120000
b1 (
b1 /
1+
1*
1-
b11 #
b11 '
b11 2
b11 %
#130000
1!
0*
0-
00
b11 )
b0 #
b0 '
b11 "
b11 &
b0 2
b11 1
b11 $
b0 %
#140000
1*
1-
b1 #
b1 '
b1 2
b1 %
#150000
0!
0*
0-
10
b10 #
b10 '
b10 2
b10 %
#160000
1*
1-
b11 #
b11 '
b11 2
b11 %
#170000
0+
b10 (
b10 /
1.
0!
0*
0-
00
b0 )
b1 ,
b0 #
b0 '
b100 "
b100 &
b0 2
b100 1
b100 $
b0 %
#180000
b0 (
b0 /
0.
1*
1-
b1 #
b1 '
b1 2
b1 %
#190000
1!
b10 (
b10 /
1.
0*
0-
10
b10 #
b10 '
b10 2
b10 %
#200000
0!
b0 (
b0 /
0.
1*
1-
b11 #
b11 '
b11 2
b11 %
#210000
1!
1+
b11 (
b11 /
1.
0*
0-
00
b1 )
b0 #
b0 '
b101 "
b101 &
b0 2
b101 1
b101 $
b0 %
#220000
0!
0+
b0 (
b0 /
0.
1*
1-
b1 #
b1 '
b1 2
b1 %
#230000
1!
1+
b11 (
b11 /
1.
0*
0-
10
b10 #
b10 '
b10 2
b10 %
#240000
0!
0+
b0 (
b0 /
0.
1*
1-
b11 #
b11 '
b11 2
b11 %
#250000
b10 (
b10 /
1.
0*
0-
00
b10 )
b0 #
b0 '
b110 "
b110 &
b0 2
b110 1
b110 $
b0 %
#260000
1!
1+
b1 (
b1 /
0.
1*
1-
b1 #
b1 '
b1 2
b1 %
#270000
0+
b10 (
b10 /
1.
1!
0*
0-
10
b10 #
b10 '
b10 2
b10 %
#280000
0!
1+
b1 (
b1 /
0.
1*
1-
b11 #
b11 '
b11 2
b11 %
#290000
b11 (
b11 /
1.
1!
0*
0-
00
b11 )
b0 #
b0 '
b111 "
b111 &
b0 2
b111 1
b111 $
b0 %
#300000
b1 (
b1 /
0.
1*
1-
b1 #
b1 '
b1 2
b1 %
#310000
b11 (
b11 /
1.
1!
0*
0-
10
b10 #
b10 '
b10 2
b10 %
#320000
0!
b1 (
b1 /
0.
1*
1-
b11 #
b11 '
b11 2
b11 %
#330000
b0 (
b0 /
0+
0!
0*
0-
00
b0 )
b10 ,
b0 #
b0 '
b1000 "
b1000 &
b0 2
b1000 1
b1000 $
b0 %
#340000
b10 (
b10 /
1.
1*
1-
b1 #
b1 '
b1 2
b1 %
#350000
b0 (
b0 /
0.
0!
0*
0-
10
b10 #
b10 '
b10 2
b10 %
#360000
1!
b10 (
b10 /
1.
1*
1-
b11 #
b11 '
b11 2
b11 %
#370000
1+
b1 (
b1 /
0.
1!
0*
0-
00
b1 )
b0 #
b0 '
b1001 "
b1001 &
b0 2
b1001 1
b1001 $
b0 %
#380000
0!
0+
b10 (
b10 /
1.
1*
1-
b1 #
b1 '
b1 2
b1 %
#390000
1+
b1 (
b1 /
0.
0!
0*
0-
10
b10 #
b10 '
b10 2
b10 %
#400000
1!
0+
b10 (
b10 /
1.
1*
1-
b11 #
b11 '
b11 2
b11 %
#410000
b0 (
b0 /
0.
0!
0*
0-
00
b10 )
b0 #
b0 '
b1010 "
b1010 &
b0 2
b1010 1
b1010 $
b0 %
#420000
1!
1+
b11 (
b11 /
1.
1*
1-
b1 #
b1 '
b1 2
b1 %
#430000
0!
0+
b0 (
b0 /
0.
0*
0-
10
b10 #
b10 '
b10 2
b10 %
#440000
1!
1+
b11 (
b11 /
1.
1*
1-
b11 #
b11 '
b11 2
b11 %
#450000
b1 (
b1 /
0.
0*
0-
00
b11 )
b0 #
b0 '
b1011 "
b1011 &
b0 2
b1011 1
b1011 $
b0 %
#460000
b11 (
b11 /
1.
1*
1-
b1 #
b1 '
b1 2
b1 %
#470000
0!
b1 (
b1 /
0.
0*
0-
10
b10 #
b10 '
b10 2
b10 %
#480000
1!
b11 (
b11 /
1.
1*
1-
b11 #
b11 '
b11 2
b11 %
#490000
0!
b10 (
b10 /
0+
0*
0-
00
b0 )
b11 ,
b0 #
b0 '
b1100 "
b1100 &
b0 2
b1100 1
b1100 $
b0 %
#500000
1*
1-
b1 #
b1 '
b1 2
b1 %
#510000
1!
0*
0-
10
b10 #
b10 '
b10 2
b10 %
#520000
1*
1-
b11 #
b11 '
b11 2
b11 %
#530000
b11 (
b11 /
1+
1!
0*
0-
00
b1 )
b0 #
b0 '
b1101 "
b1101 &
b0 2
b1101 1
b1101 $
b0 %
#540000
0!
b10 (
b10 /
0+
1*
1-
b1 #
b1 '
b1 2
b1 %
#550000
b11 (
b11 /
1+
1!
0*
0-
10
b10 #
b10 '
b10 2
b10 %
#560000
b10 (
b10 /
0+
1*
1-
b11 #
b11 '
b11 2
b11 %
#570000
0!
0*
0-
00
b10 )
b0 #
b0 '
b1110 "
b1110 &
b0 2
b1110 1
b1110 $
b0 %
#580000
1!
b11 (
b11 /
1+
1*
1-
b1 #
b1 '
b1 2
b1 %
#590000
b10 (
b10 /
0+
0*
0-
10
b10 #
b10 '
b10 2
b10 %
#600000
b11 (
b11 /
1+
1*
1-
b11 #
b11 '
b11 2
b11 %
#610000
0*
0-
00
b11 )
b0 #
b0 '
b1111 "
b1111 &
b0 2
b1111 1
b1111 $
b0 %
#620000
1*
1-
b1 #
b1 '
b1 2
b1 %
#630000
0*
0-
10
b10 #
b10 '
b10 2
b10 %
#640000
1*
1-
b11 #
b11 '
b11 2
b11 %
#650000
b10000 $
b100 %
